sde_simulator/__init__.py
sde_simulator/sde_simulator.py
sde_simulator-0.1.92.dist-info/METADATA
sde_simulator-0.1.92.dist-info/WHEEL
sde_simulator-0.1.92.dist-info/top_level.txt
sde_simulator-0.1.92.dist-info/RECORD
